{"version":1,"resource":"file:///home/raphy/dev/ument/components/ui/button.tsx","entries":[{"id":"ZHm9.tsx","timestamp":1741605877823},{"id":"5078.tsx","timestamp":1741605893158},{"id":"ZaZY.tsx","timestamp":1741677600422},{"id":"glj3.tsx","timestamp":1741677624214},{"id":"zPLv.tsx","timestamp":1741677723952},{"id":"ntx2.tsx","timestamp":1741677774141},{"id":"ntlT.tsx","timestamp":1741677795872},{"id":"Y6cZ.tsx","timestamp":1741677814934},{"id":"N4uW.tsx","timestamp":1741677844515},{"id":"aAXn.tsx","timestamp":1741791319027},{"id":"qaiF.tsx","timestamp":1741791370698},{"id":"LxZu.tsx","timestamp":1741791387799},{"id":"ERJd.tsx","timestamp":1741791422633},{"id":"srtx.tsx","timestamp":1741791469138},{"id":"UauQ.tsx","timestamp":1741791728199},{"id":"bLfA.tsx","timestamp":1741791745508},{"id":"nagn.tsx","timestamp":1741791766268},{"id":"DijD.tsx","timestamp":1741791785363},{"id":"okZB.tsx","timestamp":1741791859716}]}