{"version":1,"resource":"file:///home/raphy/dev/v1_ai/app/components/TimeSelection.tsx","entries":[{"id":"MR0D.tsx","timestamp":1741109502189},{"id":"eW6M.tsx","timestamp":1741109513298},{"id":"RFkT.tsx","timestamp":1741109660145},{"id":"J32E.tsx","timestamp":1741109683566},{"id":"AZEO.tsx","timestamp":1741109774027},{"id":"lx0r.tsx","timestamp":1741109788068},{"id":"2Qnk.tsx","timestamp":1741109819124},{"id":"WHQC.tsx","timestamp":1741109829198},{"id":"HRFB.tsx","timestamp":1741109844906},{"id":"e3Xi.tsx","timestamp":1741109860821},{"id":"Xmvf.tsx","timestamp":1741109877681},{"id":"42ql.tsx","timestamp":1741109899802},{"id":"yreL.tsx","timestamp":1741109926309},{"id":"Moh8.tsx","timestamp":1741109937211},{"id":"Uqdn.tsx","timestamp":1741109958328},{"id":"w11l.tsx","timestamp":1741110007568},{"id":"o4Bm.tsx","timestamp":1741110024112},{"id":"5CPP.tsx","timestamp":1741110045168},{"id":"xcdE.tsx","timestamp":1741110057233},{"id":"dWwI.tsx","timestamp":1741110071164},{"id":"Xv3O.tsx","timestamp":1741110082529},{"id":"GtGs.tsx","timestamp":1741110098900},{"id":"w4c8.tsx","timestamp":1741110112837},{"id":"vBAi.tsx","timestamp":1741110128371},{"id":"axCf.tsx","timestamp":1741110154615},{"id":"cqcV.tsx","timestamp":1741110183763},{"id":"zR2E.tsx","timestamp":1741110197052},{"id":"Tx6F.tsx","timestamp":1741110217435},{"id":"R5JG.tsx","timestamp":1741110250993},{"id":"rDf8.tsx","timestamp":1741110271528},{"id":"cqoi.tsx","timestamp":1741110344841},{"id":"zK0u.tsx","timestamp":1741110377812},{"id":"tXnQ.tsx","timestamp":1741110397190},{"id":"mCbq.tsx","timestamp":1741110413983},{"id":"1aXk.tsx","timestamp":1741110614330},{"id":"Mcjs.tsx","timestamp":1741110641541},{"id":"Eo27.tsx","timestamp":1741110745939},{"id":"PKvc.tsx","timestamp":1741111195689},{"id":"X0Od.tsx","timestamp":1741111283559},{"id":"Fllh.tsx","timestamp":1741115823352},{"id":"cMpu.tsx","timestamp":1741115877911},{"id":"swzQ.tsx","timestamp":1741116492156},{"id":"XtHX.tsx","timestamp":1741116507708},{"id":"oG3P.tsx","timestamp":1741116553823},{"id":"4Sco.tsx","timestamp":1741116624306},{"id":"SWGN.tsx","timestamp":1741116640472},{"id":"6AvV.tsx","timestamp":1741116688027},{"id":"opMr.tsx","timestamp":1741116897793},{"id":"rd11.tsx","timestamp":1741117161975},{"id":"JDa8.tsx","timestamp":1741117200424}]}